[
  {
    "severity": "high",
    "title": "Cannot place Guild Construction\u003eDiagrams",
    "details": "Cannot place full diagrams. Error: \"Diagram contains invalid components for this panel.\"",
    "guild": true,
    "solo": false,
    "pc": true,
    "mobile": true,
    "ps5": true,
    "media": [
      "https://cdn.discordapp.com/attachments/1509461162520219688/1509600307947110580/image.png?ex=6a279c18\u0026hm=8b211ba0d13942b6a001cd70addab159cc76932e6dce810e30468730ad0d2391\u0026is=6a264a98\u0026",
      "https://cdn.discordapp.com/attachments/1509461162520219688/1510928354830979173/Guild_Construction_Diagrams.mp4?ex=6a27d3af\u0026hm=a7bb83bbe85e85d6c302d1feb0c5cc052bc35c70c1797d3237baff9a2fade525\u0026is=6a26822f\u0026"
    ],
    "version": "v1.7",
    "date": "28/05/2026",
    "notes": "CN server also received this update which is problematic. Many builders use those components in their work. It's critical because days of efforts are lost because of this."
  },
  {
    "severity": "high",
    "title": "Cannot place guild diagrams component",
    "details": "Cannot place/copy any exclusive component from Guild Construction \u003e Diagrams in guild base. Error: \"This component is not available in the current panel.\"",
    "guild": true,
    "solo": false,
    "pc": true,
    "mobile": true,
    "ps5": true,
    "media": [
      "https://cdn.discordapp.com/attachments/1509461162520219688/1509499956384370688/image.png?ex=6a27e762\u0026hm=37c205da8bc6d9d2a703c6d83031d6df07d6eb1f22cfb71a88b1c558472fa7c5\u0026is=6a2695e2\u0026",
      "https://cdn.discordapp.com/attachments/1509461162520219688/1510928823716417556/Component_not_available.mp4?ex=6a27d41f\u0026hm=e378b902b1ea78b04b696e0f6412ab38648521efaf2297005b6a5253972158cd\u0026is=6a26829f\u0026"
    ],
    "version": "v1.7",
    "date": "28/05/2026",
    "notes": "Probable root cause:Cannot place Guild Construction\u003eDiagrams"
  },
  {
    "severity": "high",
    "title": "Cannot apply some custom diagrams",
    "details": "Custom/Saved guild diagrams cannot be applied in certain conditions. Error: \"Blueprint contains components that cannot be placed in the Open World.\"",
    "guild": true,
    "solo": false,
    "pc": true,
    "mobile": true,
    "ps5": true,
    "media": [],
    "version": "v1.7",
    "date": "28/05/2026",
    "notes": "Probable root cause:Cannot place Guild Construction\u003eDiagrams. Indeed, diagram can contain some components from Guild construction \u003e Diagrams"
  },
  {
    "severity": "normal",
    "title": "Cannot post edit component from diagrams",
    "details": "Unable to use edit: pick up, replace, move any components built from diagram. Error: \"Diagram component does not support this action\"",
    "guild": true,
    "solo": false,
    "pc": true,
    "mobile": true,
    "ps5": true,
    "media": [
      "https://cdn.discordapp.com/attachments/1509461162520219688/1510578703531376771/image.png?ex=6a27df8c\u0026hm=aa69702000363d91ab14eab14567f71f23bba51295aa1a6c3333f74f5451afe8\u0026is=6a268e0c\u0026"
    ],
    "version": "v1.7",
    "date": "28/05/2026",
    "notes": "Concern any component from any diagram"
  },
  {
    "severity": "normal",
    "title": "Stone platforms do not cover grass",
    "details": "Grass clips through the platform whereas platforms used to cover it before",
    "guild": true,
    "solo": false,
    "pc": true,
    "mobile": false,
    "ps5": false,
    "media": [
      "https://cdn.discordapp.com/attachments/1509461162520219688/1509844662192705596/1780043090_PJkxdw7S.png?ex=6a27d6eb\u0026hm=45d61fbdba8af251ae6f6efb160d399a0b7118e42d7832ce826fb3443bcc7241\u0026is=6a26856b\u0026"
    ],
    "version": "v1.7",
    "date": "28/05/2026",
    "notes": "TODO: verify solo, mobile/ps5"
  },
  {
    "severity": "low",
    "title": "Theater stage missing shadow figure",
    "details": "\"Theater Stage\" Single Use component has no shadow as of now",
    "guild": true,
    "solo": false,
    "pc": true,
    "mobile": false,
    "ps5": false,
    "media": [
      "https://cdn.discordapp.com/attachments/1509461162520219688/1509593828435431535/image.png?ex=6a27960f\u0026hm=06e3956ae58b32cc5be77a9007c3f03020d45064da7c761f29c4ab25f7c36e17\u0026is=6a26448f\u0026"
    ],
    "version": "v1.7",
    "date": "28/05/2026",
    "notes": "TODO: verify solo, mobile/ps5"
  },
  {
    "severity": "low",
    "title": "Guqin table cloth mat disappears when rotate",
    "details": "Appearance is different when post rotating",
    "guild": true,
    "solo": false,
    "pc": true,
    "mobile": false,
    "ps5": false,
    "media": [
      "https://cdn.discordapp.com/attachments/1483447711499030633/1510180358753226763/image.png?ex=6a27be0f\u0026hm=3d8de5fbcecf2459ab1554c9131651b0dbe3d231d65f8c460a3701203cbad55c\u0026is=6a266c8f\u0026",
      "https://cdn.discordapp.com/attachments/1483447711499030633/1510180359411859613/image.png?ex=6a27be0f\u0026hm=10999ed98f4e3577a989d28049a253298cb15a7addeff8272aacc88bb067f33b\u0026is=6a266c8f\u0026"
    ],
    "version": "v1.7",
    "date": "30/05/2026",
    "notes": "Not tested on other platform and solo"
  },
  {
    "severity": "normal",
    "title": "Cannot rotate component on 2nd axis on mobile",
    "details": "We can rotate now on PC but not on another platform",
    "guild": true,
    "solo": true,
    "pc": false,
    "mobile": true,
    "ps5": true,
    "media": [],
    "version": "v1.7",
    "date": "30/05/2026",
    "notes": ""
  },
  {
    "severity": "fixed",
    "title": "Interactive components missing from guilds",
    "details": "All interactive building components are missing from guild base, including all interactable chairs and furniture. They no longer appear but still count toward the component cap.",
    "guild": true,
    "solo": false,
    "pc": true,
    "mobile": true,
    "ps5": true,
    "media": [],
    "version": "v1.7",
    "date": "28/05/2026",
    "notes": ""
  },
  {
    "severity": "low",
    "title": "Cannot rotate diagram on 2nd axis",
    "details": "You can rotate on first axis but not second one",
    "guild": true,
    "solo": true,
    "pc": true,
    "mobile": true,
    "ps5": true,
    "media": [
      "https://cdn.discordapp.com/attachments/1509461162520219688/1511029696891191436/Cannot-rotate-2nd-diagram.mp4?ex=6a278951\u0026hm=fe9ce55a8c5f1b70904cb0eebe4b25003a94b8efc3cf16264ba336d9f9c4e8a4\u0026is=6a2637d1\u0026"
    ],
    "version": "v1.7",
    "date": "01/06/2026",
    "notes": ""
  },
  {
    "severity": "normal",
    "title": "Cannot save diagram if copyright more than 30%",
    "details": "After diagram placement you need to be the builder of more than 70% components to be able to save the diagram",
    "guild": true,
    "solo": true,
    "pc": true,
    "mobile": true,
    "ps5": true,
    "media": [
      "https://cdn.discordapp.com/attachments/1509461162520219688/1511152433492132000/2026-06-02_00_17_08-Where_Winds_Meet.jpg?ex=6a2752df\u0026hm=9ae12971822aecd01d0888667d1cc17d638483557926f2a6d2329506470bb6dd\u0026is=6a26015f\u0026",
      "https://cdn.discordapp.com/attachments/1509461162520219688/1511152432267268157/2026-06-02_01_06_40-Where_Winds_Meet.jpg?ex=6a2752df\u0026hm=bc2cca4f60289f6df2a1ee7414e32be11d237c92dd816986a31798df0371f5f9\u0026is=6a26015f\u0026"
    ],
    "version": "v1.7",
    "date": "02/06/2026",
    "notes": "Considered as a bug. Let's say you are 2 builders in a guild and the work repartition is 69% and 21%. Nobody can save the diagram."
  },
  {
    "severity": "normal",
    "title": "Cannot rotate on 2nd axis for mobile and ps5",
    "details": "There is no know button to be able to rotate on 2nd axis",
    "guild": false,
    "solo": false,
    "pc": false,
    "mobile": true,
    "ps5": true,
    "media": [],
    "version": "v1.7",
    "date": "02/06/2026",
    "notes": "PC has this feature so should other platforms"
  },
  {
    "severity": "high",
    "title": "Components cannot be placed at ground level",
    "details": "The treshold to determine underground component seems too high for some components",
    "guild": true,
    "solo": false,
    "pc": false,
    "mobile": true,
    "ps5": false,
    "media": [
      "https://cdn.discordapp.com/attachments/1483447711499030633/1511571396671701093/Screenshot_20260603_102216_com_netease_yysls_MessiahNativeActivity.jpg?ex=6a278790\u0026hm=fb4178e582f9b4c555c75d9a44e10e8250e6d944076b3608117e0450cca2067a\u0026is=6a263610\u0026",
      "https://cdn.discordapp.com/attachments/1483447711499030633/1511944494143246386/ScreenRecording_06-04-2026_12-06-14_1.mov?ex=6a279189\u0026hm=bb98fa4589ab2656753f0a9e5aa174cc4bc15fdbdac8b9c3a5469b11acb0a92b\u0026is=6a264009\u0026",
      "https://cdn.discordapp.com/attachments/1483447711499030633/1513157083489632398/SVID_20260607_192226_1.mp4?ex=6a275d99\u0026hm=1113b955183afd1fad070d5c9830115aebbb3d19516a0c3fa4fa5c93ee62fc97\u0026is=6a260c19\u0026"
    ],
    "version": "v1.7",
    "date": "03/06/2026",
    "notes": "Recent bug as of 4/6/2026. It has not been noticed in first days of v1.7"
  },
  {
    "severity": "high",
    "title": "Components are passing through when placing",
    "details": "Most components don't properly lean on other components, instead they phase through to the middle",
    "guild": true,
    "solo": true,
    "pc": false,
    "mobile": true,
    "ps5": false,
    "media": [
      "https://cdn.discordapp.com/attachments/1483483683456286911/1511771129021206629/Screen_Recording_20260603_183743_Where_Winds_Meet.mp4?ex=6a2798d4\u0026hm=03caa4f34096e97a645fe7cbc3a1eaa7f9f1746335d77fc7f32bf73328df1282\u0026is=6a264754\u0026",
      "https://cdn.discordapp.com/attachments/1483483683456286911/1511732864369168474/Screenshot_20260603_160223_Where_Winds_Meet.jpg?ex=6a277531\u0026hm=3d3c409543f4e7ad26e543d483896aee6ccecca53206a9dd88111c86d68d3d3c\u0026is=6a2623b1\u0026"
    ],
    "version": "v1.7",
    "date": "03/06/2026",
    "notes": "Recent bug as of 4/6/2026. It has not been noticed in first days of v1.7"
  },
  {
    "severity": "high",
    "title": "Items disappear in construction mode",
    "details": "Approaching components or moving camera can make them disappear on mobile",
    "guild": true,
    "solo": false,
    "pc": false,
    "mobile": true,
    "ps5": false,
    "media": [
      "https://cdn.discordapp.com/attachments/1483447711499030633/1511944440183521310/ScreenRecording_06-04-2026_12-03-39_1.mov?ex=6a27917d\u0026hm=f7abfbc0fde3d03e30deb9758732ffa07dd6cad68dbeb7583591132042e56b59\u0026is=6a263ffd\u0026",
      "https://cdn.discordapp.com/attachments/1483447711499030633/1510909201612935229/ScreenRecording_06-01-2026_17-06-42_1.mov?ex=6a27c1d9\u0026hm=56623d136ecd4aa02b2d2fc14c9e7ffc767b771c54cd233b66d9894224e9d70a\u0026is=6a267059\u0026",
      "https://cdn.discordapp.com/attachments/1483447711499030633/1510909242838745088/ScreenRecording_06-01-2026_16-35-08_1.mov?ex=6a27c1e2\u0026is=6a267062\u0026hm=ee80c05f8a82be4cfe93a6e885110ade23df105f02dd966c928238390e26abf5\u0026",
      "https://cdn.discordapp.com/attachments/1483447711499030633/1512014693735207013/ScreenRecording_06-04-2026_16-45-20_1.mov?ex=6a27d2ea\u0026hm=dab55adba5780e6dd4543f51c42c3c7ae9ad2b08763ba65d397684d9e39bcac1\u0026is=6a26816a\u0026",
      "https://cdn.discordapp.com/attachments/1483447711499030633/1510909424653303929/ScreenRecording_06-01-2026_16-52-00_1.mov?ex=6a27c20e\u0026hm=28ed62cc6872498f2658fd4ffef5d5b75cd37d246ff5a20e6259b4ef96e84e68\u0026is=6a26708e\u0026",
      "https://cdn.discordapp.com/attachments/1483447711499030633/1513109397256274000/ScreenRecording_06-07-2026_19-12-53_1.mov?ex=6a27d9f0\u0026hm=bdcec4281101dff57d10751f69ca2f9333881793131e777288ac2ed70a78bcff\u0026is=6a268870\u0026",
      "https://cdn.discordapp.com/attachments/1483447711499030633/1513109398103261314/ScreenRecording_06-07-2026_19-11-58_1.mov?ex=6a27d9f0\u0026hm=fdbe06ee54d39073de8878e1ff4386d9d8cbb7afae0084940bb47a503b85e582\u0026is=6a268870\u0026"
    ],
    "version": "v1.7",
    "date": "04/06/2026",
    "notes": "Before only large components items disappear now all items as of 4/6/2026"
  },
  {
    "severity": "high",
    "title": "Cannot pick up and place back components",
    "details": "In edit mode picking up components is buggy",
    "guild": true,
    "solo": false,
    "pc": false,
    "mobile": true,
    "ps5": false,
    "media": [
      "https://cdn.discordapp.com/attachments/1483447711499030633/1511944464153706556/ScreenRecording_06-04-2026_12-04-33_1.mov?ex=6a279182\u0026hm=f167b56af7cfa65ce80de748892fd29e4b479f2c330324cdf89ee458dacd53df\u0026is=6a264002\u0026"
    ],
    "version": "v1.7",
    "date": "04/06/2026",
    "notes": "Recent bug as of 4/6/2026. It has not been noticed in first days of v1.7"
  },
  {
    "severity": "high",
    "title": "Items cannot auto-snap",
    "details": "Even when selecting auto-snap, items will not snap",
    "guild": false,
    "solo": false,
    "pc": false,
    "mobile": true,
    "ps5": false,
    "media": [
      "https://cdn.discordapp.com/attachments/1483483683456286911/1512145505633829016/Screen_Recording_20260604_191503_Where_Winds_Meet.mp4?ex=6a27a3fe\u0026hm=bba547f73ed0d286a74e35474467b507da963a8b7d2cd0ae598f42deedb900da\u0026is=6a26527e\u0026"
    ],
    "version": "v1.7",
    "date": "04/06/2026",
    "notes": "Recent bug as of 4/6/2026. This was not an known issue prior to this date."
  },
  {
    "severity": "high",
    "title": "Cannot batch place or batch delete components",
    "details": "When attempting to place or delete multiple components by clicking and dragging, the feature does not work",
    "guild": false,
    "solo": false,
    "pc": false,
    "mobile": true,
    "ps5": false,
    "media": [
      "https://cdn.discordapp.com/attachments/1483483683456286911/1512145506665762906/Screen_Recording_20260604_192237_Where_Winds_Meet.mp4?ex=6a27a3ff\u0026hm=4858124132bedafb0c5659790975383cca14bdad312c1c10ee4f554593737106\u0026is=6a26527f\u0026"
    ],
    "version": "v1.7",
    "date": "04/06/2026",
    "notes": "Recent bug as of 4/6/2026. This was not an known issue prior to this date."
  },
  {
    "severity": "normal",
    "title": "Small diagrams placement is tedious",
    "details": "The hitbox is too large we should be able to blend into already existing components not avoid them at all cost",
    "guild": true,
    "solo": false,
    "pc": true,
    "mobile": false,
    "ps5": false,
    "media": [],
    "version": "v1.7",
    "date": "05/06/2026",
    "notes": ""
  },
  {
    "severity": "low",
    "title": "Stuck after small diagram placement teleport",
    "details": "Can't go out of build mode had to leave the guild base to unstuck",
    "guild": true,
    "solo": false,
    "pc": true,
    "mobile": false,
    "ps5": false,
    "media": [
      "https://cdn.discordapp.com/attachments/1483447711499030634/1512388648363098122/2026-06-05_11-28-24.mp4?ex=6a27ddb0\u0026hm=3d1226d946e1a89cbe79cc644bd9d83c3a3069a5ae1b3920ec3732df151fafed\u0026is=6a268c30\u0026"
    ],
    "version": "v1.7",
    "date": "05/06/2026",
    "notes": ""
  },
  {
    "severity": "low",
    "title": "Cannot edit component from filled diagram",
    "details": "Can't Pickup/Replace/Move component from a diagram. We should be able to once we have removed the outline.",
    "guild": true,
    "solo": false,
    "pc": true,
    "mobile": false,
    "ps5": false,
    "media": [
      "https://cdn.discordapp.com/attachments/1509461162520219688/1512451859032444968/image.png?ex=6a276fcf\u0026hm=d3e8b2de413ba7365f721e8a06734c0c5c8322acc6358f3fdde13312b0a4e658\u0026is=6a261e4f\u0026"
    ],
    "version": "v1.7",
    "date": "05/06/2026",
    "notes": ""
  },
  {
    "severity": "normal",
    "title": "Vegetation toggle not working.",
    "details": "Vegetation is deleted even if the clear vegetation toggle is off.",
    "guild": true,
    "solo": true,
    "pc": true,
    "mobile": true,
    "ps5": true,
    "media": [
      "https://cdn.discordapp.com/attachments/1483447711499030633/1512831912048328725/image.png?ex=6a278042\u0026hm=b70b0c63db9e8ec594fe2b862dba6a72e505a396cbd7a81c00a50434706e3cc4\u0026is=6a262ec2\u0026"
    ],
    "version": "v1.7",
    "date": "06/06/2026",
    "notes": "Ongoing bug as far as i remember since the beginning."
  }
]