{
	"1005769840218345482": {
		"username": "itzgatta"
	},
	"1026278810632593449": {
		"username": "rebbie00"
	},
	"1088250197810876506": {
		"username": "kanootjohnson"
	},
	"1095266335942000720": {
		"username": "weixi_soul"
	},
	"1153304236369653780": {
		"username": "romy_aina"
	},
	"1155975280016510987": {
		"username": "solanyaaa"
	},
	"116352783573057543": {
		"username": "unknown#12"
	},
	"1175049136618356782": {
		"username": "lea30683",
		"nickname": "Xela"
	},
	"1179100397466570884": {
		"username": "foxi.kate"
	},
	"1179308934599806996": {
		"username": "chumimaru01"
	},
	"1206102405595402243": {
		"username": "yamssandwich"
	},
	"1243701587344494704": {
		"username": "darlarim"
	},
	"1247940218246664293": {
		"username": "omg_090"
	},
	"132197255993229312": {
		"username": "patriot8791",
		"nickname": "Veneslash"
	},
	"132216422897156096": {
		"username": "alscend"
	},
	"1324936700857942059": {
		"username": "babysoul123_01037"
	},
	"1354978954284498974": {
		"username": "dear.lambdoll"
	},
	"136305348544823296": {
		"username": "interns"
	},
	"1383186476547702814": {
		"username": "keroberoxe"
	},
	"1385727534653771908": {
		"username": "sirenzsmile_16621"
	},
	"1386339923031752886": {
		"username": "itskkulgomi"
	},
	"1421831986028347542": {
		"username": "lashin667"
	},
	"143460371297075201": {
		"username": "unknown#1"
	},
	"1441888058306986177": {
		"username": "sung_jiin_wooo"
	},
	"144331936008110081": {
		"username": "si9183"
	},
	"1444109001246638195": {
		"username": "brucebannermad"
	},
	"1447831981579829321": {
		"username": "unknown#5"
	},
	"1447976780743839755": {
		"username": "dianaeaeo"
	},
	"1457093658573803641": {
		"username": "melinashka."
	},
	"1460140885030207590": {
		"username": "unknown#3"
	},
	"1464740199522111734": {
		"username": "yalishandaz"
	},
	"1471559358474092626": {
		"username": "orla30557"
	},
	"147954531433447424": {
		"username": "armgarion"
	},
	"1483492595953959004": {
		"username": "Ruby"
	},
	"149790526076354561": {
		"username": "coincouinade",
		"nickname": "Ahlyam"
	},
	"150870411863654400": {
		"username": "hmu."
	},
	"163408870734168065": {
		"username": "moodswing_rob",
		"nickname": "MooDSwinG"
	},
	"172567438490206209": {
		"username": "nextbeat"
	},
	"173674529099481098": {
		"username": "kryptid420"
	},
	"193368856998182912": {
		"username": "kysentra"
	},
	"201256155350171649": {
		"username": "king0fgames",
		"nickname": "yar"
	},
	"203542084689461249": {
		"username": "neosmaug"
	},
	"204728779980013568": {
		"username": "bearzzn"
	},
	"208562383214346240": {
		"username": "atal91"
	},
	"210795943837171712": {
		"username": "squeezie_"
	},
	"219138199631560705": {
		"username": "tavu"
	},
	"221965752482267136": {
		"username": "nashaiem",
		"nickname": "Yuèshi"
	},
	"224541417748299777": {
		"username": "azerelx"
	},
	"226512871687847938": {
		"username": "opm.goat"
	},
	"234648656022601739": {
		"username": "khiwhi"
	},
	"249313949210771466": {
		"username": "haka54"
	},
	"250096111950364672": {
		"username": "cursed5679"
	},
	"254307352528814080": {
		"username": "_m4d3",
		"nickname": "Avyendha"
	},
	"254759458771566592": {
		"username": "tearies"
	},
	"261855225034440704": {
		"username": "arikato_"
	},
	"263355353624870913": {
		"username": "theonlyomega"
	},
	"275527292736897024": {
		"username": "kamijoan"
	},
	"276118224079421440": {
		"username": "anomalyzombie"
	},
	"282548012016861187": {
		"username": "unknown#6"
	},
	"283225632941277184": {
		"username": ".meln."
	},
	"293781262315814913": {
		"username": "imderiisa"
	},
	"306349275305082880": {
		"username": "rengoku._.kyujuro"
	},
	"320282723325444098": {
		"username": "blancdb"
	},
	"322044967717437440": {
		"username": "miekesenpai"
	},
	"328891482691862532": {
		"username": "phandelope"
	},
	"336962135613636610": {
		"username": "shirahime_lp"
	},
	"337924618926948356": {
		"username": "maelyss"
	},
	"344062569457123328": {
		"username": "izanagi_cz"
	},
	"362930492296921089": {
		"username": "nshki_"
	},
	"363830510243545088": {
		"username": "keishalily"
	},
	"373638396360392705": {
		"username": "john.they.them."
	},
	"376083682076917762": {
		"username": "machikadowave"
	},
	"376950312721711118": {
		"username": "_babe",
		"nickname": "영미 (B)"
	},
	"383472747986026507": {
		"username": "headshot_proto"
	},
	"384447715385540619": {
		"username": "moonyart"
	},
	"387307552607830016": {
		"username": "anarky67"
	},
	"395904796453896192": {
		"username": "unknown#10"
	},
	"402186999542317057": {
		"username": "rhspa"
	},
	"403803695008972801": {
		"username": "aatmameraa"
	},
	"408665758852317185": {
		"username": "ota1096"
	},
	"420252715332141057": {
		"username": "lollypopllp"
	},
	"429941440186023940": {
		"username": "ducklord13"
	},
	"433671641269010432": {
		"username": "shan_dy"
	},
	"446093296167813122": {
		"username": "mirage_strays"
	},
	"449306791088488468": {
		"username": "queseje"
	},
	"450875663185084438": {
		"username": "mellowkoi"
	},
	"456702943463342091": {
		"username": "3sixmafia"
	},
	"478873772607406101": {
		"username": "jinzzz77"
	},
	"480935180539002883": {
		"username": "frappe_chino"
	},
	"491013443453714436": {
		"username": "inactiveaj"
	},
	"497092404474806273": {
		"username": "unknown#8"
	},
	"505726679897866242": {
		"username": "ravala"
	},
	"507478894857945098": {
		"username": "creedstone.",
		"nickname": "Bella/ShenLiuMei"
	},
	"511489842614632448": {
		"username": "takyli"
	},
	"512276516697145346": {
		"username": "aevsu",
		"nickname": "KaiTingLi"
	},
	"516258129374347275": {
		"username": "krewain",
		"nickname": "Kraujas"
	},
	"524459554117910528": {
		"username": "zuxilor4541"
	},
	"524615660115066909": {
		"username": "unknown#1"
	},
	"552631204294426632": {
		"username": "dustybawls4575"
	},
	"569139020102238208": {
		"username": "hbx"
	},
	"603234320408379392": {
		"username": "aryastark1676"
	},
	"609980399732523018": {
		"username": "silentj_."
	},
	"612708264588869679": {
		"username": "rend",
		"nickname": "Harass"
	},
	"626525163416059935": {
		"username": "letheglitch"
	},
	"627074072030871552": {
		"username": ".nennen"
	},
	"633927708971237387": {
		"username": "rye6659"
	},
	"645262444746506284": {
		"username": "tan6174"
	},
	"645387989978972234": {
		"username": "unknown#2"
	},
	"649417342731943936": {
		"username": "soapcosy"
	},
	"690759797951430716": {
		"username": "descharges8994"
	},
	"700659572603355187": {
		"username": "giuxyria"
	},
	"707387939944136704": {
		"username": "unknown#9"
	},
	"713213214099505152": {
		"username": "elysiahoh"
	},
	"721162051338371182": {
		"username": "maadworld"
	},
	"721510597958828183": {
		"username": "palmbark",
		"nickname": "WindXP"
	},
	"732304387480748075": {
		"username": "iiangelii"
	},
	"734725361597808723": {
		"username": "suriez06"
	},
	"773253240498159636": {
		"username": "minhee."
	},
	"773381328866377740": {
		"username": "greg3rdd"
	},
	"785485177996050442": {
		"username": "barashfr"
	},
	"786742305541062706": {
		"username": "keichai"
	},
	"794903975052836915": {
		"username": "stanley_dante"
	},
	"813776087279599626": {
		"username": "rastawar"
	},
	"814010958603091988": {
		"username": "tcatxyz"
	},
	"814547014565888050": {
		"username": "creamydesu"
	},
	"823276464769990698": {
		"username": "unknown#4"
	},
	"831958815850627123": {
		"username": "eterias_"
	},
	"864588758765535274": {
		"username": "unknown#7"
	},
	"873122821566517248": {
		"username": "diana.dnt"
	},
	"889286804497371186": {
		"username": "alearae"
	},
	"892650959233245194": {
		"username": "dyosam_"
	},
	"912740347120074812": {
		"username": "animasano."
	},
	"925992493466648587": {
		"username": "akakushi."
	},
	"935748222515810435": {
		"username": "eulreiss."
	},
	"943017992294367253": {
		"username": "baked.crowtato"
	},
	"952613053290151987": {
		"username": "pyouup"
	},
	"959076147826688090": {
		"username": "yanju5"
	},
	"959509483913101413": {
		"username": "selkyxxii."
	},
	"963012140443263066": {
		"username": "unknown#11"
	},
	"997247599880978603": {
		"username": "carnivore21"
	}
}